pyKlay/__init__.py
pyKlay/__version__.py
pyKlay/jvm.py
pyKlay/klay.py
pyKlay/data/dictionary/binary/system/emission.bin
pyKlay/data/dictionary/binary/system/transition.bin
pyKlay/data/dictionary/text/user/dic.user
pyKlay/data/dictionary/text/user/fwd.user
pyKlay/libs/klay-python-wrapper-0.3.jar
pyKlay/libs/py4j0.10.8.1.jar
klay4py-0.3.dist-info/LICENSE
klay4py-0.3.dist-info/METADATA
klay4py-0.3.dist-info/WHEEL
klay4py-0.3.dist-info/top_level.txt
klay4py-0.3.dist-info/RECORD
