Metadata-Version: 2.1
Name: klay4py
Version: 0.3
Summary: KLAY4py is for python user considering to use KLAY.
Home-page: https://github.com/ks-shim/klay4py
Author: KS-SHIM
Author-email: dwayne.shim@gmail.com
License: Apache 2.0
Download-URL: https://github.com/klay4py/pyKlay/releases/download/0.3/klay4py-0.3.tar.gz
Keywords: KLAY,Korean Language AnalYzer
Platform: UNKNOWN
Classifier: Development Status :: 3 - Alpha
Classifier: Environment :: Console
Classifier: Intended Audience :: Developers
Classifier: Intended Audience :: Education
Classifier: Intended Audience :: Information Technology
Classifier: Intended Audience :: Science/Research
Classifier: License :: OSI Approved :: Apache Software License
Classifier: Natural Language :: Korean
Classifier: Programming Language :: Java
Classifier: Programming Language :: Python :: 3 :: Only
Classifier: Topic :: Scientific/Engineering :: Information Analysis
Classifier: Topic :: Software Development :: Libraries :: Java Libraries
Classifier: Topic :: Text Processing :: Linguistic
Requires-Dist: py4j (==0.10.8.1)
Provides-Extra: test
